multistream_select/__init__.py
multistream_select/multiselect.py
multistream_select/multiselect_client.py
multistream_select/multiselect_client_interface.py
multistream_select/multiselect_communicator.py
multistream_select/multiselect_communicator_interface.py
multistream_select/multiselect_muxer_interface.py
test/__init__.py
test/test_multiselect.py
test/test_multistream.py
test/test_utils.py
multistream_select-0.1.3.dist-info/LICENSE
multistream_select-0.1.3.dist-info/METADATA
multistream_select-0.1.3.dist-info/WHEEL
multistream_select-0.1.3.dist-info/top_level.txt
multistream_select-0.1.3.dist-info/RECORD
