Metadata-Version: 2.1
Name: multistream-select
Version: 0.1.3
Summary: an implementation of the multistream protocol in python
Home-page: https://github.com/dheatovwil/py-multistream-select
Author: Tiong Tay
Author-email: tgtay@outlook.com
License: MIT
Keywords: ipfs multistream-select
Platform: UNKNOWN
Classifier: Development Status :: 3 - Alpha
Classifier: Intended Audience :: Developers
Classifier: License :: OSI Approved :: MIT License
Classifier: Programming Language :: Python :: 3.6
Classifier: Programming Language :: Python :: 3.7
Provides-Extra: dev
Requires-Dist: check-manifest ; extra == 'dev'
Provides-Extra: test
Requires-Dist: coverage ; extra == 'test'
